kst/__about__.py
kst/__init__.py
kst/console.py
kst/diff.py
kst/exceptions.py
kst/git.py
kst/utils.py
kst/api/__init__.py
kst/api/apps.py
kst/api/client.py
kst/api/payload.py
kst/api/profiles.py
kst/api/resource_base.py
kst/api/scripts.py
kst/api/self_service.py
kst/cli/__init__.py
kst/cli/common.py
kst/cli/new.py
kst/cli/utility.py
kst/cli/_resources/gitignore.txt
kst/cli/_resources/new_repo_readme.md
kst/cli/profile/__init__.py
kst/cli/profile/common.py
kst/cli/profile/delete.py
kst/cli/profile/list.py
kst/cli/profile/new.py
kst/cli/profile/pull.py
kst/cli/profile/push.py
kst/cli/profile/show.py
kst/cli/profile/sync.py
kst/cli/script/__init__.py
kst/cli/script/common.py
kst/cli/script/delete.py
kst/cli/script/list.py
kst/cli/script/new.py
kst/cli/script/pull.py
kst/cli/script/push.py
kst/cli/script/show.py
kst/cli/script/sync.py
kst/repository/__init__.py
kst/repository/content.py
kst/repository/custom_profile.py
kst/repository/custom_script.py
kst/repository/info.py
kst/repository/member_base.py
kst/repository/repository.py
kst-1.2.0.dist-info/METADATA
kst-1.2.0.dist-info/WHEEL
kst-1.2.0.dist-info/entry_points.txt
kst-1.2.0.dist-info/licenses/LICENSE
kst-1.2.0.dist-info/RECORD
