Metadata-Version: 2.4
Name: kst
Version: 1.2.0
Summary: Kandji Sync Toolkit, a utility for local management of Kandji resources.
Project-URL: Homepage, https://github.com/kandji-inc/kst
Project-URL: Repository, https://github.com/kandji-inc/kst.git
Project-URL: Bug Tracker, https://github.com/kandji-inc/kst/issues
License-Expression: MIT
License-File: LICENSE
Keywords: kandji,kandji-sync-toolkit
Classifier: Development Status :: 5 - Production/Stable
Classifier: Environment :: Console
Classifier: License :: OSI Approved :: MIT License
Classifier: Operating System :: MacOS
Classifier: Operating System :: Microsoft :: Windows
Classifier: Operating System :: Unix
Classifier: Programming Language :: Python :: 3
Classifier: Programming Language :: Python :: 3.12
Classifier: Programming Language :: Python :: 3.13
Classifier: Topic :: Software Development :: Version Control :: Git
Classifier: Topic :: System :: Systems Administration
Requires-Python: >=3.12
Requires-Dist: click<8.2.0
Requires-Dist: platformdirs>=4.3.6
Requires-Dist: pydantic>=2.9.2
Requires-Dist: requests>=2.32.3
Requires-Dist: ruamel-yaml>=0.18.6
Requires-Dist: typer>=0.15.1
